django_model_viewer/__init__.py
django_model_viewer/admin.py
django_model_viewer/apps.py
django_model_viewer/middleware.py
django_model_viewer/models.py
django_model_viewer/tests.py
django_model_viewer/urls.py
django_model_viewer/views.py
django_model_viewer/migrations/__init__.py
django_model_viewer/templates/main.html
django_model_viewer/templates/django_template_viewer/main.html
modelsviewer/__init__.py
modelsviewer/admin.py
modelsviewer/apps.py
modelsviewer/models.py
modelsviewer/tests.py
modelsviewer/urls.py
modelsviewer/views.py
modelsviewer/migrations/__init__.py
django_model_viewer-1.1.3.dist-info/METADATA
django_model_viewer-1.1.3.dist-info/WHEEL
django_model_viewer-1.1.3.dist-info/top_level.txt
django_model_viewer-1.1.3.dist-info/RECORD
