Metadata-Version: 2.1
Name: django-model-viewer
Version: 1.1.3
Summary: A useful tool for viewing Django models, their relationships and functions.
Home-page: https://github.com/lysykot/django-model-viewer
Author: Mikołaj Łysakowski
Author-email: mikolaj.lysakowski01@gmail.com
License: This software may be used, modified, and distributed freely for personal, educational, or research purposes. Commercial use, including but not limited to selling or offering the software as part of a product or service, is prohibited without prior written permission from the author.
Platform: UNKNOWN
Classifier: Framework :: Django
Classifier: Programming Language :: Python :: 3
Classifier: License :: Other/Proprietary License
Classifier: Operating System :: OS Independent
Requires-Dist: Django
